[
    {
        "provinsi_awal":"Sumatra Selatan",
        "provinsi_tujuan":"Sumatera Selatan",
        "kabupaten_awal":"Palembang",
        "kabupaten_tujuan":"Prabumulih",
        "kecamatan_awal":null,
        "kecamatan_tujuan":null,
        "min_charge":10,
        "price":2500,
        "satuan_estimasi_waktu":"Hari",
        "estimasi_tercepat":1,
        "estimasi_terlama":2,
        "vendorId":"cm0docj6t00007vfjqmhm2jxm"
    },
    {
        "provinsi_awal":"Sumatra Selatan",
        "provinsi_tujuan":"Sumatera Selatan",
        "kabupaten_awal":"Palembang",
        "kabupaten_tujuan":"Muara Enim",
        "kecamatan_awal":null,
        "kecamatan_tujuan":null,
        "min_charge":10,
        "price":2500,
        "satuan_estimasi_waktu":"Hari",
        "estimasi_tercepat":1,
        "estimasi_terlama":2,
        "vendorId":"cm0docj6t00007vfjqmhm2jxm"
    },
    {
        "provinsi_awal":"Sumatra Selatan",
        "provinsi_tujuan":"Sumatera Selatan",
        "kabupaten_awal":"Palembang",
        "kabupaten_tujuan":"Lahat",
        "kecamatan_awal":null,
        "kecamatan_tujuan":null,
        "min_charge":10,
        "price":2500,
        "satuan_estimasi_waktu":"Hari",
        "estimasi_tercepat":1,
        "estimasi_terlama":2,
        "vendorId":"cm0docj6t00007vfjqmhm2jxm"
    },
    {
        "provinsi_awal":"Sumatra Selatan",
        "provinsi_tujuan":"Sumatera Selatan",
        "kabupaten_awal":"Palembang",
        "kabupaten_tujuan":"Pagar Alam",
        "kecamatan_awal":null,
        "kecamatan_tujuan":null,
        "min_charge":10,
        "price":5000,
        "satuan_estimasi_waktu":"Hari",
        "estimasi_tercepat":1,
        "estimasi_terlama":2,
        "vendorId":"cm0docj6t00007vfjqmhm2jxm"
    },
    {
        "provinsi_awal":"Sumatra Selatan",
        "provinsi_tujuan":"Sumatera Selatan",
        "kabupaten_awal":"Palembang",
        "kabupaten_tujuan":"Baturaja",
        "kecamatan_awal":null,
        "kecamatan_tujuan":null,
        "min_charge":10,
        "price":2500,
        "satuan_estimasi_waktu":"Hari",
        "estimasi_tercepat":1,
        "estimasi_terlama":2,
        "vendorId":"cm0docj6t00007vfjqmhm2jxm"
    },
    {
        "provinsi_awal":"Sumatra Selatan",
        "provinsi_tujuan":"Sumatera Selatan",
        "kabupaten_awal":"Palembang",
        "kabupaten_tujuan":"Martapura",
        "kecamatan_awal":null,
        "kecamatan_tujuan":null,
        "min_charge":10,
        "price":3000,
        "satuan_estimasi_waktu":"Hari",
        "estimasi_tercepat":1,
        "estimasi_terlama":2,
        "vendorId":"cm0docj6t00007vfjqmhm2jxm"
    },
    {
        "provinsi_awal":"Sumatra Selatan",
        "provinsi_tujuan":"Sumatera Selatan",
        "kabupaten_awal":"Palembang",
        "kabupaten_tujuan":"Belitang",
        "kecamatan_awal":null,
        "kecamatan_tujuan":null,
        "min_charge":10,
        "price":3000,
        "satuan_estimasi_waktu":"Hari",
        "estimasi_tercepat":1,
        "estimasi_terlama":2,
        "vendorId":"cm0docj6t00007vfjqmhm2jxm"
    },
    {
        "provinsi_awal":"Sumatra Selatan",
        "provinsi_tujuan":"Sumatera Selatan",
        "kabupaten_awal":"Palembang",
        "kabupaten_tujuan":"Muaradua",
        "kecamatan_awal":null,
        "kecamatan_tujuan":null,
        "min_charge":10,
        "price":4000,
        "satuan_estimasi_waktu":"Hari",
        "estimasi_tercepat":1,
        "estimasi_terlama":2,
        "vendorId":"cm0docj6t00007vfjqmhm2jxm"
    },
    {
        "provinsi_awal":"Sumatra Selatan",
        "provinsi_tujuan":"Sumatera Selatan",
        "kabupaten_awal":"Palembang",
        "kabupaten_tujuan":"Kayu Agung",
        "kecamatan_awal":null,
        "kecamatan_tujuan":null,
        "min_charge":10,
        "price":3000,
        "satuan_estimasi_waktu":"Hari",
        "estimasi_tercepat":1,
        "estimasi_terlama":2,
        "vendorId":"cm0docj6t00007vfjqmhm2jxm"
    },
    {
        "provinsi_awal":"Sumatra Selatan",
        "provinsi_tujuan":"Sumatera Selatan",
        "kabupaten_awal":"Palembang",
        "kabupaten_tujuan":"Tugumulyo",
        "kecamatan_awal":null,
        "kecamatan_tujuan":null,
        "min_charge":10,
        "price":5000,
        "satuan_estimasi_waktu":"Hari",
        "estimasi_tercepat":1,
        "estimasi_terlama":2,
        "vendorId":"cm0docj6t00007vfjqmhm2jxm"
    },
    {
        "provinsi_awal":"Sumatra Selatan",
        "provinsi_tujuan":"Sumatera Selatan",
        "kabupaten_awal":"Palembang",
        "kabupaten_tujuan":"Betung",
        "kecamatan_awal":null,
        "kecamatan_tujuan":null,
        "min_charge":10,
        "price":2500,
        "satuan_estimasi_waktu":"Hari",
        "estimasi_tercepat":1,
        "estimasi_terlama":2,
        "vendorId":"cm0docj6t00007vfjqmhm2jxm"
    },
    {
        "provinsi_awal":"Sumatra Selatan",
        "provinsi_tujuan":"Sumatera Selatan",
        "kabupaten_awal":"Palembang",
        "kabupaten_tujuan":"Sekayu",
        "kecamatan_awal":null,
        "kecamatan_tujuan":null,
        "min_charge":10,
        "price":2500,
        "satuan_estimasi_waktu":"Hari",
        "estimasi_tercepat":1,
        "estimasi_terlama":2,
        "vendorId":"cm0docj6t00007vfjqmhm2jxm"
    },
    {
        "provinsi_awal":"Sumatra Selatan",
        "provinsi_tujuan":"Sumatera Selatan",
        "kabupaten_awal":"Palembang",
        "kabupaten_tujuan":"Sungai Lilin",
        "kecamatan_awal":null,
        "kecamatan_tujuan":null,
        "min_charge":10,
        "price":2500,
        "satuan_estimasi_waktu":"Hari",
        "estimasi_tercepat":1,
        "estimasi_terlama":2,
        "vendorId":"cm0docj6t00007vfjqmhm2jxm"
    },
    {
        "provinsi_awal":"Sumatra Selatan",
        "provinsi_tujuan":"Sumatera Selatan",
        "kabupaten_awal":"Palembang",
        "kabupaten_tujuan":"Babat Toman",
        "kecamatan_awal":null,
        "kecamatan_tujuan":null,
        "min_charge":10,
        "price":3000,
        "satuan_estimasi_waktu":"Hari",
        "estimasi_tercepat":1,
        "estimasi_terlama":2,
        "vendorId":"cm0docj6t00007vfjqmhm2jxm"
    },
    {
        "provinsi_awal":"Sumatra Selatan",
        "provinsi_tujuan":"Sumatera Selatan",
        "kabupaten_awal":"Palembang",
        "kabupaten_tujuan":"Lubuk Linggau",
        "kecamatan_awal":null,
        "kecamatan_tujuan":null,
        "min_charge":10,
        "price":3000,
        "satuan_estimasi_waktu":"Hari",
        "estimasi_tercepat":1,
        "estimasi_terlama":2,
        "vendorId":"cm0docj6t00007vfjqmhm2jxm"
    },
    {
        "provinsi_awal":"Sumatra Selatan",
        "provinsi_tujuan":"Sumatera Selatan",
        "kabupaten_awal":"Palembang",
        "kabupaten_tujuan":"Curup",
        "kecamatan_awal":null,
        "kecamatan_tujuan":null,
        "min_charge":10,
        "price":5000,
        "satuan_estimasi_waktu":"Hari",
        "estimasi_tercepat":1,
        "estimasi_terlama":2,
        "vendorId":"cm0docj6t00007vfjqmhm2jxm"
    }
]